FoolishAuth/__init__.py
FoolishAuth/authentication.py
FoolishAuth/settings.py
foolish_auth-1.1.1.dist-info/METADATA
foolish_auth-1.1.1.dist-info/WHEEL
foolish_auth-1.1.1.dist-info/top_level.txt
foolish_auth-1.1.1.dist-info/RECORD
